dad/__init__.py
dad/augs.py
dad/benchmarks/__init__.py
dad/benchmarks/hpatches.py
dad/benchmarks/megadepth.py
dad/benchmarks/num_inliers.py
dad/benchmarks/scannet.py
dad/checkpoint.py
dad/datasets/__init__.py
dad/datasets/megadepth.py
dad/detectors/__init__.py
dad/detectors/dedode_detector.py
dad/detectors/third_party/__init__.py
dad/detectors/third_party/harrisaff.py
dad/detectors/third_party/hesaff.py
dad/detectors/third_party/lightglue/__init__.py
dad/detectors/third_party/lightglue/aliked.py
dad/detectors/third_party/lightglue/disk.py
dad/detectors/third_party/lightglue/dog_hardnet.py
dad/detectors/third_party/lightglue/lightglue.py
dad/detectors/third_party/lightglue/sift.py
dad/detectors/third_party/lightglue/superpoint.py
dad/detectors/third_party/lightglue/utils.py
dad/detectors/third_party/lightglue_detector.py
dad/detectors/third_party/rekd/config.py
dad/detectors/third_party/rekd/geometry_tools.py
dad/detectors/third_party/rekd/model/REKD.py
dad/detectors/third_party/rekd/model/kernels.py
dad/detectors/third_party/rekd/model/load_models.py
dad/detectors/third_party/rekd/rekd.py
dad/logging.py
dad/loss.py
dad/matchers/__init__.py
dad/matchers/roma.py
dad/reward_functions/__init__.py
dad/reward_functions/constant_reward.py
dad/train.py
dad/types.py
dad/utils.py
dad_detector-0.2.2.dist-info/WHEEL
dad_detector-0.2.2.dist-info/METADATA
dad_detector-0.2.2.dist-info/RECORD
