Metadata-Version: 2.3
Name: dad-detector
Version: 0.2.2
Summary: Definitely a Detector, DeDoDe and DISK, DaD and DaD.
Requires-Dist: einops>=0.8.1
Requires-Dist: numpy>=1.24
Requires-Dist: opencv-python>=4.11.0.86
Requires-Dist: pillow>=11.0.0
Requires-Dist: torch>=2.4
Requires-Dist: torchvision>=0.21.0
Requires-Python: >=3.9
